LICENSE
MANIFEST.in
NEWS
README.md
dev-requirements.txt
requirements.txt
setup.py
sopel_modules/__init__.py
sopel_modules.habitica.egg-info/PKG-INFO
sopel_modules.habitica.egg-info/SOURCES.txt
sopel_modules.habitica.egg-info/dependency_links.txt
sopel_modules.habitica.egg-info/namespace_packages.txt
sopel_modules.habitica.egg-info/requires.txt
sopel_modules.habitica.egg-info/top_level.txt
sopel_modules/habitica/__init__.py
sopel_modules/habitica/chat.py
sopel_modules/habitica/common.py
sopel_modules/habitica/hero.py