Metadata-Version: 1.0
Name: sopel-modules.habitica
Version: 0.1.0
Summary: Sopel module for Habitica
Home-page: http://github.com/ttheuer/sopel-habitica
Author: Tobias Theuer
Author-email: theuer@hardbop.org
License: MIT License
Platform: UNKNOWN
